lvmscp/__init__.py
lvmscp/__main__.py
lvmscp/controller.py
lvmscp/delegate.py
lvmscp/actor/__init__.py
lvmscp/actor/actor.py
lvmscp/actor/commands/__init__.py
lvmscp/actor/commands/etr.py
lvmscp/actor/commands/focus.py
lvmscp/actor/commands/hardware_status.py
lvmscp/etc/LVM_100kHz.acf
lvmscp/etc/lvmscp.yml
lvmscp/etc/schema.json
sdss_lvmscp-0.10.8.dist-info/METADATA
sdss_lvmscp-0.10.8.dist-info/WHEEL
sdss_lvmscp-0.10.8.dist-info/entry_points.txt
sdss_lvmscp-0.10.8.dist-info/licenses/LICENSE.md
sdss_lvmscp-0.10.8.dist-info/RECORD
