Metadata-Version: 2.4
Name: sdss-lvmscp
Version: 0.10.8
Summary: LVM spectrograph control package.
Project-URL: Homepage, https://github.com/sdss/lvmscp
Project-URL: Repository, https://github.com/sdss/lvmscp
Project-URL: Documentation, https://sdss-lvmscp.readthedocs.org
Author-email: José Sánchez-Gallego <gallegoj@uw.edu>, Changgon Kim <changgonkim@khu.ac.kr>
License: BSD-3-Clause
License-File: LICENSE.md
Requires-Python: <4,>=3.10
Requires-Dist: sdss-archon>=0.15.5
Requires-Dist: sdsstools>=1.9.2
Provides-Extra: fitsio
Requires-Dist: fitsio>=1.2.2; extra == 'fitsio'
